phik/simulation.py
phik/binning.py
phik/definitions.py
phik/bivariate.py
phik/phik.py
phik/entry_points.py
phik/__init__.py
phik/betainc.py
phik/outliers.py
phik/utils.py
phik/significance.py
phik/resources.py
phik/statistics.py
phik/report.py
phik/data_quality.py
phik/simcore/asa159.hpp
phik/simcore/simulation.hpp
phik/simcore/__init__.py
phik/simcore/asa159.cpp
phik/simcore/bindings.cpp
phik/decorators/pandas.py
phik/decorators/__init__.py
phik/lib/_phik_simulation_core.cpython-312-darwin.so
phik/data/fake_insurance_data.csv.gz
phik/notebooks/phik_tutorial_basic.ipynb
phik/notebooks/phik_tutorial_spark.ipynb
phik/notebooks/phik_tutorial_advanced.ipynb
phik-0.12.4.dist-info/RECORD
phik-0.12.4.dist-info/WHEEL
phik-0.12.4.dist-info/entry_points.txt
phik-0.12.4.dist-info/METADATA
phik-0.12.4.dist-info/licenses/LICENSE
phik-0.12.4.dist-info/licenses/NOTICE
