Metadata-Version: 2.1
Name: phik
Version: 0.12.4
Summary: Phi_K correlation analyzer library
Author-Email: KPMG N.V. The Netherlands <kave@kpmg.com>
Classifier: Development Status :: 4 - Beta
Classifier: License :: OSI Approved :: MIT License
Classifier: Programming Language :: Python :: 3 :: Only
Classifier: Programming Language :: Python :: 3.8
Classifier: Programming Language :: Python :: 3.9
Classifier: Programming Language :: Python :: 3.10
Classifier: Programming Language :: Python :: 3.11
Classifier: Programming Language :: Python :: 3.12
Requires-Python: >=3.8
Requires-Dist: numpy>=1.18.0
Requires-Dist: scipy>=1.5.2
Requires-Dist: pandas>=0.25.1
Requires-Dist: matplotlib>=2.2.3
Requires-Dist: joblib>=0.14.1
Requires-Dist: pytest>=4.0.2; extra == "test"
Requires-Dist: pytest-pylint>=0.13.0; extra == "test"
Provides-Extra: test
